behave_parallel_runners/__init__.py
behave_parallel_runners/pool.py
behave_parallel_runners/runner.py
behave_parallel_runners/task.py
behave_parallel_runners/workers/__init__.py
behave_parallel_runners/workers/interpreter.py
behave_parallel_runners/workers/process.py
behave_parallel_runners/workers/thread.py
behave_parallel_runners-1.1.0.dist-info/METADATA
behave_parallel_runners-1.1.0.dist-info/WHEEL
behave_parallel_runners-1.1.0.dist-info/RECORD
