Metadata-Version: 2.3
Name: behave-parallel-runners
Version: 1.1.0
Summary: 
License: MIT
Author: Lokkina Olesia
Requires-Python: <4.0,>=3.10
Classifier: License :: OSI Approved :: MIT License
Classifier: Programming Language :: Python :: 3
Classifier: Programming Language :: Python :: 3.10
Classifier: Programming Language :: Python :: 3.11
Classifier: Programming Language :: Python :: 3.12
Classifier: Programming Language :: Python :: 3.13
Requires-Dist: behave (>=1.3.0,<2.0.0)
Requires-Dist: sortedcontainers (>=2.4.0,<3.0.0)
